physictools/__init__.py
physictools/data.py
physictools-0.0.16.dist-info/METADATA
physictools-0.0.16.dist-info/WHEEL
physictools-0.0.16.dist-info/top_level.txt
physictools-0.0.16.dist-info/RECORD
