Metadata-Version: 2.2
Name: physictools
Version: 0.0.16
Summary: A simple module to assist in physics bachelor
Author: Paul Welte
Requires-Dist: scipy
Requires-Dist: numpy
Dynamic: author
Dynamic: requires-dist
Dynamic: summary
